<annotation>
	<folder>摩托车</folder>
	<filename>摩托车_53.jpg</filename>
	<path>C:\Users\ligua\Desktop\data\data\images\摩托车\摩托车_53.jpg</path>
	<source>
		<database>Unknown</database>
	</source>
	<size>
		<width>570</width>
		<height>473</height>
		<depth>3</depth>
	</size>
	<segmented>0</segmented>
	<object>
		<name>摩托车</name>
		<pose>Unspecified</pose>
		<truncated>1</truncated>
		<difficult>0</difficult>
		<bndbox>
			<xmin>54</xmin>
			<ymin>218</ymin>
			<xmax>570</xmax>
			<ymax>465</ymax>
		</bndbox>
	</object>
</annotation>
